eo_satellites/__init__.py
eo_satellites/_modidx.py
eo_satellites/satellite.py
eo_satellites-0.0.1.dist-info/LICENSE
eo_satellites-0.0.1.dist-info/METADATA
eo_satellites-0.0.1.dist-info/WHEEL
eo_satellites-0.0.1.dist-info/entry_points.txt
eo_satellites-0.0.1.dist-info/top_level.txt
eo_satellites-0.0.1.dist-info/RECORD
