Metadata-Version: 2.1
Name: eo-satellites
Version: 0.0.1
Summary: satellite registry
Home-page: https://github.com/KBodolai/eo-satellites/
Author: KBodolai
Author-email: kristian@space-intelligence.com
License: Apache Software License 2.0
Keywords: nbdev
Platform: UNKNOWN
Classifier: Development Status :: 3 - Alpha
Classifier: Intended Audience :: Developers
Classifier: Natural Language :: English
Classifier: Programming Language :: Python :: 3.8
Classifier: Programming Language :: Python :: 3.9
Classifier: Programming Language :: Python :: 3.10
Classifier: License :: OSI Approved :: Apache Software License
Requires-Python: >=3.8
Provides-Extra: dev
